shut/__init__.py
shut/__main__.py
shut/py.typed
shut/builders/__init__.py
shut/builders/core.py
shut/builders/setuptools.py
shut/changelog/__init__.py
shut/changelog/manager.py
shut/changelog/render.py
shut/changelog/v1.py
shut/changelog/v2.py
shut/changelog/v3.py
shut/checkers/__init__.py
shut/checkers/base.py
shut/checkers/generic.py
shut/checkers/monorepo.py
shut/checkers/package.py
shut/commands/__init__.py
shut/commands/classifiers.py
shut/commands/conda_forge.py
shut/commands/init.py
shut/commands/license.py
shut/commands/changelog/__init__.py
shut/commands/commons/__init__.py
shut/commands/commons/bump.py
shut/commands/commons/checks.py
shut/commands/commons/new.py
shut/commands/commons/status.py
shut/commands/mono/__init__.py
shut/commands/mono/bump.py
shut/commands/mono/checks.py
shut/commands/mono/install.py
shut/commands/mono/new.py
shut/commands/mono/publish.py
shut/commands/mono/status.py
shut/commands/mono/test.py
shut/commands/mono/update.py
shut/commands/pkg/__init__.py
shut/commands/pkg/build.py
shut/commands/pkg/bump.py
shut/commands/pkg/checks.py
shut/commands/pkg/format.py
shut/commands/pkg/install.py
shut/commands/pkg/new.py
shut/commands/pkg/publish.py
shut/commands/pkg/requirements.py
shut/commands/pkg/run.py
shut/commands/pkg/status.py
shut/commands/pkg/test.py
shut/commands/pkg/update.py
shut/data/__init__.py
shut/data/license_templates/Apache2.txt
shut/data/license_templates/BSD2.txt
shut/data/license_templates/BSD3.txt
shut/data/license_templates/BSD4.txt
shut/data/license_templates/MIT.txt
shut/data/templates/github-action.yml
shut/data/templates/pylintrc-shut.ini
shut/model/__init__.py
shut/model/abstract.py
shut/model/author.py
shut/model/changelog.py
shut/model/linter.py
shut/model/monorepo.py
shut/model/package.py
shut/model/publish.py
shut/model/release.py
shut/model/requirements.py
shut/model/target.py
shut/model/utils.py
shut/model/version.py
shut/publishers/__init__.py
shut/publishers/core.py
shut/publishers/warehouse.py
shut-0.21.1.dist-info/LICENSE.txt
shut-0.21.1.dist-info/METADATA
shut-0.21.1.dist-info/WHEEL
shut-0.21.1.dist-info/entry_points.txt
shut-0.21.1.dist-info/top_level.txt
shut-0.21.1.dist-info/RECORD
