Metadata-Version: 2.1
Name: shut
Version: 0.21.1
Summary: Automates the heavy lifting of release and distribution management for pure Python packages.
Home-page: https://github.com/NiklasRosenstein/shut
Author: Niklas Rosenstein
Author-email: rosensteinniklas@gmail.com
License: MIT
Platform: UNKNOWN
Requires-Python: >=3.7.0,<4.0.0
Requires-Dist: beautifulsoup4 (<5.0.0,>=4.8.1)
Requires-Dist: databind.core (<2.0.0,>=1.1.2)
Requires-Dist: databind.json (<2.0.0,>=1.1.2)
Requires-Dist: click (<9.0,>=7.1)
Requires-Dist: networkx (<3.0.0,>=2.4.0)
Requires-Dist: nr.fs (<2.0.0,>=1.5.0)
Requires-Dist: nr.parsing.date (<2.0.0,>=1.0.3)
Requires-Dist: nr.proxy (<2.0.0,>=1.0.0)
Requires-Dist: nr.pylang.utils (<1.0.0,>=0.0.1)
Requires-Dist: nr.utils.git (<0.2.0,>=0.1.3)
Requires-Dist: nr.stream (<1.0.0,>=0.2.2)
Requires-Dist: requests (<3.0.0,>=2.22.0)
Requires-Dist: packaging (<21.0.0,>=20.1.0)
Requires-Dist: PyYAML (<6.0.0,>=5.1.0)
Requires-Dist: termcolor (<2.0.0,>=1.1.0)
Requires-Dist: typing-extensions (<4.0.0,>=3.10.0.0)
Requires-Dist: twine
Requires-Dist: wheel
Requires-Dist: Mako (<2.0.0,>=1.1.5)
Provides-Extra: test
Requires-Dist: pytest ; extra == 'test'
Requires-Dist: mypy ; extra == 'test'
Requires-Dist: types-beautifulsoup4 ; extra == 'test'
Requires-Dist: types-click ; extra == 'test'
Requires-Dist: types-requests ; extra == 'test'
Requires-Dist: types-PyYAML ; extra == 'test'
Requires-Dist: types-setuptools ; extra == 'test'
Requires-Dist: types-termcolor ; extra == 'test'
